pr_pro/__init__.py
pr_pro/abbreviations.py
pr_pro/configs.py
pr_pro/example.py
pr_pro/exercise.py
pr_pro/functions.py
pr_pro/program.py
pr_pro/sets.py
pr_pro/workout_component.py
pr_pro/workout_session.py
pr_pro/exercises/common.py
pr_pro/pdf_export/__init__.py
pr_pro/pdf_export/pdf_generator.py
pr_pro/streamlit_vis/__init__.py
pr_pro/streamlit_vis/session.py
pr_pro/streamlit_vis/sets.py
pr_pro/streamlit_vis/state.py
pr_pro/streamlit_vis/streamlit_app.py
pr_pro/streamlit_vis/workout_component.py
pr_pro/streamlit_vis/workout_component_boxed.py
pr_pro-1.1.0.dist-info/METADATA
pr_pro-1.1.0.dist-info/WHEEL
pr_pro-1.1.0.dist-info/entry_points.txt
pr_pro-1.1.0.dist-info/RECORD
