Metadata-Version: 2.4
Name: pr-pro
Version: 1.1.0
Summary: PRogramming PROgrams is a Python library for defining training programs.
Project-URL: Homepage, https://github.com/rolandstolz/pr_pro
Author-email: Roland Stolz <roland.stolz9@gmail.com>
Classifier: License :: OSI Approved :: MIT License
Classifier: Operating System :: OS Independent
Classifier: Programming Language :: Python :: 3
Requires-Python: >=3.12
Requires-Dist: pandas>=2.3.0
Requires-Dist: pydantic>=2.11.4
Provides-Extra: dev
Requires-Dist: pytest-cov>=6.1.1; extra == 'dev'
Requires-Dist: pytest>=8.4.0; extra == 'dev'
Provides-Extra: vis
Requires-Dist: fpdf2>=2.8.4; extra == 'vis'
Requires-Dist: matplotlib>=3.10.3; extra == 'vis'
Requires-Dist: streamlit>=1.45.1; extra == 'vis'
Requires-Dist: watchdog>=6.0.0; extra == 'vis'
